kopp/__init__.py
kopp/__main__.py
kopp/__version__.py
kopp/main.py
kopp-0.2.1.dist-info/entry_points.txt
kopp-0.2.1.dist-info/WHEEL
kopp-0.2.1.dist-info/METADATA
kopp-0.2.1.dist-info/license_files/LICENSE
kopp-0.2.1.dist-info/RECORD
