Metadata-Version: 2.1
Name: kopp
Version: 0.2.1
Summary: Korean postpositions processing package
License: MIT
Keywords: korean,kopp,josa
Author-email: dowon <ks2515@naver.com>
Requires-Python: >=3.7
Classifier: License :: OSI Approved :: MIT License
Classifier: Natural Language :: Korean
Classifier: Programming Language :: Python :: 3
Classifier: Topic :: Text Processing :: Linguistic
Project-URL: Repository, https://github.com/Bing-su/kopp
